dcpoc/__init__.py
dcpoc/prime_numbers.py
grampy-0.9.1.dist-info/LICENSE
grampy-0.9.1.dist-info/METADATA
grampy-0.9.1.dist-info/WHEEL
grampy-0.9.1.dist-info/top_level.txt
grampy-0.9.1.dist-info/RECORD
