Metadata-Version: 2.1
Name: grampy
Version: 0.9.1
Summary: A small package to work with prime numbers
Home-page: https://github.com/clement-bonnet/medium-first-package
Author: Alex G
Author-email: alex.g@gmail.com
License: UNKNOWN
Platform: UNKNOWN
Classifier: Programming Language :: Python :: 3
Classifier: License :: OSI Approved :: MIT License
Classifier: Operating System :: OS Independent
